README
setup.py
bin/srcyr2lat
srcyr2lat/__init__.py
srcyr2lat.egg-info/PKG-INFO
srcyr2lat.egg-info/SOURCES.txt
srcyr2lat.egg-info/dependency_links.txt
srcyr2lat.egg-info/top_level.txt
srcyr2lat.egg-info/zip-safe