Metadata-Version: 1.0
Name: srcyr2lat
Version: 0.1.2
Summary: Translate serbian cyrillic text to latin version
Home-page: http://github.com/nesh/srcyr2lat
Author: Nebojsa Djordjevic
Author-email: djnesh@gmail.com
License: BSD
Platform: UNKNOWN
